<oai_dc:dc xmlns:oai_dc="http://www.openarchives.org/OAI/2.0/oai_dc/" xmlns:dc="http://purl.org/dc/elements/1.1/" xmlns:xsi="http://www.w3.org/2001/XMLSchema-instance" xsi:schemaLocation="http://www.openarchives.org/OAI/2.0/oai_dc/  http://www.openarchives.org/OAI/2.0/oai_dc.xsd"><id>3445</id>
	<dc:title xml:lang="de-DE">Herrschaft vom Pferderücken – Reisekönigtum zur Zeit Heinrichs IV.</dc:title>
	<dc:creator>Tschiedel, Torben</dc:creator>
	<dc:description xml:lang="de-DE">Die Hauptstadt und das Land gehören für moderne Menschen untrennbar zusammen. Eines geht ohne das andere nicht. Bereits in der Grundschule lernen wir die entsprechenden Begriffspaare auswendig. In Hauptstädten wird Politik gemacht, sie sind die Schaltzentrale ihres Landes und der Ort, an dem das Parlament, viele wichtige Ministerien sowie ausländische Konsulate und Botschaften zu finden sind; meistens in einem eigenen Regierungsviertel. Für uns ist die Hauptstadt heute selbstverständlich ein Synonym für das Zentrum der Macht und für diejenigen, die politische Entscheidungen treffen. Demnach „entscheidet Berlin“, man fragt, „was Washington eigentlich denkt“, „welche Zusicherungen Moskau gemacht hat“ und was „Peking dazu sagt“.</dc:description>
	<dc:publisher xml:lang="de-DE">Mittelalter Digital</dc:publisher>
	<dc:date>2021-07-05</dc:date>
	<dc:type>info:eu-repo/semantics/article</dc:type>
	<dc:type>info:eu-repo/semantics/publishedVersion</dc:type>
	<dc:type xml:lang="de-DE">Begutachter Beitrag</dc:type>
	<dc:format>application/pdf</dc:format>
	<dc:identifier>https://www.uni-muenster.de/Ejournals/index.php/mittelalterdigi/article/view/3445</dc:identifier>
	<dc:identifier>10.17879/mittelalterdigital-2021-3445</dc:identifier>
	<dc:source xml:lang="de-DE">Mittelalter Digital; Bd. 2 Nr. 1 (2021): A.D. 1050; 12-31</dc:source>
	<dc:source>2747-9757</dc:source>
	<dc:language>deu</dc:language>
	<dc:relation>https://www.uni-muenster.de/Ejournals/index.php/mittelalterdigi/article/view/3445/3443</dc:relation>
	<dc:relation>https://www.uni-muenster.de/Ejournals/index.php/mittelalterdigi/article/view/3445/3444</dc:relation>
	<dc:relation>urn:nbn:de:hbz:6:3-mittelalterdigital-2021-34434</dc:relation>
	<dc:relation>urn:nbn:de:hbz:6:3-mittelalterdigital-2021-34442</dc:relation>
	<dc:rights xml:lang="de-DE">Copyright (c) 2021 Torben Tschiedel</dc:rights>
	<dc:rights xml:lang="de-DE">http://creativecommons.org/licenses/by/4.0</dc:rights>
</oai_dc:dc>