<oai_dc:dc xmlns:oai_dc="http://www.openarchives.org/OAI/2.0/oai_dc/" xmlns:dc="http://purl.org/dc/elements/1.1/" xmlns:xsi="http://www.w3.org/2001/XMLSchema-instance" xsi:schemaLocation="http://www.openarchives.org/OAI/2.0/oai_dc/  http://www.openarchives.org/OAI/2.0/oai_dc.xsd"><id>524</id>
	<dc:title xml:lang="de-DE">Sozialethik in postdemokratischen Zeiten. Bericht über das 13. Berliner Werkstattgespräch  der Sozialethiker(innen) 2012</dc:title>
	<dc:creator>Küppers, Arnd</dc:creator>
	<dc:subject xml:lang="de-DE">Grundlagen</dc:subject>
	<dc:subject xml:lang="de-DE">Demokratie</dc:subject>
	<dc:subject xml:lang="de-DE">Globalisierung</dc:subject>
	<dc:subject xml:lang="de-DE">Tagung</dc:subject>
	<dc:description xml:lang="de-DE">[kein Abstract]</dc:description>
	<dc:publisher xml:lang="de-DE">Institut für Christliche Sozialwissenschaften (ICS), Westfälische Wilhelms-Universität Münster </dc:publisher>
	<dc:date>2012-11-13</dc:date>
	<dc:type>info:eu-repo/semantics/article</dc:type>
	<dc:type>info:eu-repo/semantics/publishedVersion</dc:type>
	<dc:type xml:lang="de-DE">Nicht begutachtete Artikel, Artikel auf Einladung</dc:type>
	<dc:format>application/pdf</dc:format>
	<dc:identifier>https://www.uni-muenster.de/Ejournals/index.php/jcsw/article/view/524</dc:identifier>
	<dc:source xml:lang="de-DE">Jahrbuch für Christliche Sozialwissenschaften; Bd. 53 (2012): Sozialethik für eine Gesellschaft des langen Lebens; 295–301</dc:source>
	<dc:source xml:lang="en-US">Jahrbuch für Christliche Sozialwissenschaften; Vol. 53 (2012): Sozialethik für eine Gesellschaft des langen Lebens; 295–301</dc:source>
	<dc:source>2196-6265</dc:source>
	<dc:source>0075-2584</dc:source>
	<dc:language>deu</dc:language>
	<dc:relation>https://www.uni-muenster.de/Ejournals/index.php/jcsw/article/view/524/pdf</dc:relation>
	<dc:relation>urn:nbn:de:hbz:6:3-20120821111</dc:relation>
	<dc:relation>10.17879/jcsw-2012-512</dc:relation>
</oai_dc:dc>