<mets:mets xmlns:mets="http://www.loc.gov/METS/" xmlns:mods="http://www.loc.gov/mods/v3" xmlns:xlink="http://www.w3.org/1999/xlink">
    <mets:dmdSec ID="DMD_wwu-journals_3748">
        <mets:mdWrap MIMETYPE="text/xml" MDTYPE="MODS">
            <mets:xmlData>
                <mods xmlns="http://www.loc.gov/mods/v3" version="3.7" xmlns:vl="http://visuallibrary.net/vl">
                    <titleInfo lang="ger">
                        <title>Glaubwürdig seelsorglich handeln! Wie geht das?</title>
                    </titleInfo>
                    <name type="personal">
                        <displayForm>Nauer, Doris</displayForm>
                        <namePart type="family">Nauer</namePart>
                        <namePart type="given">Doris</namePart>
                        <role>
                            <roleTerm type="code" authority="marcrelator">ctb</roleTerm>
                        </role>
                    </name>
                    <typeOfResource>text</typeOfResource>
                    <genre authority="dini">article</genre>
                    <originInfo>
                        <dateIssued encoding="w3cdtf" keyDate="yes">2022-01-24</dateIssued>
                    </originInfo>
                    <language>
                        <languageTerm type="code" authority="iso639-2b">ger</languageTerm>
                    </language>
                    <physicalDescription>
                        <extent unit="page">15</extent>
                    </physicalDescription>
                    <abstract lang="ger">Historische Hypotheken untergraben bis ins 21. Jahrhundert hinein die Glaubwürdigkeit christlicher Seelsorger*innen. Verloren gegangene Glaubwürdigkeit kann zurückgewonnen werden, wenn Seelsorger*innen über ein theoretisches Seelsorgeverständnis verfügen, das ihr alltägliches seelsorgliches Handeln sowohl für Christ*innen als auch für Nicht-Christ*innen (wieder) glaubwürdig macht.
Historical burdens have tended to undermine the credibility of Christian chaplains, even up to the present day. Lost credibility can be regained if chaplains embrace a pastoral care theory that leads (again) to a credible daily pastoral practice, namely, one conceived as credible by both Christians and non-Christians.</abstract>
                    <subject lang="ger">
                    </subject>
                    <subject lang="eng">
                    </subject>
                    <relatedItem type="host">
                        <titleInfo>
                            <title>Zeitschrift für Pastoraltheologie (ZPTh)</title>
                        </titleInfo>
                        <originInfo>
                            <publisher type="issn">Zeitschrift für Pastoraltheologie (ZPTh)</publisher>
                        </originInfo>
                        <identifier type="issn">0555-9308</identifier>
                        <part>
                            <detail type="volume">
                                <number>41</number>
                            </detail>
                            <detail type="issue">
                                <number>2</number>
                            </detail>
                            <extent unit="page">
                                <start>25</start>
                                <end>39</end>
                            </extent>
                        </part>
                    </relatedItem>
                    <identifier type="urn">urn:nbn:de:hbz:6:3-zpth-2021-37957</identifier>
                    <recordInfo>
                        <recordIdentifier>wwu-journals_3748</recordIdentifier>
                    </recordInfo>
                    <extension>
                        <vl:doctype>oaArticle</vl:doctype>
                    </extension>
                </mods>
            </mets:xmlData>
        </mets:mdWrap>
    </mets:dmdSec>
    <mets:fileSec>
        <mets:fileGrp USE="pdf upload">
            <mets:file MIMETYPE="application/pdf" ID="FILE0_wwu-journals_3748">
                <mets:FLocat xlink:href="https://www.uni-muenster.de/Ejournals/index.php/zpth/article/download/3748/3795" LOCTYPE="URL"/>
            </mets:file>
        </mets:fileGrp>
    </mets:fileSec>
    <mets:structMap TYPE="LOGICAL">
        <mets:div TYPE="document" ID="wwu-journals_3748" DMDID="DMD_wwu-journals_3748">
            <mets:fptr FILEID="FILE0_wwu-journals_3748"/>
        </mets:div>
    </mets:structMap>
</mets:mets>
